tantivy_fork_arm-0.22.1.dist-info/METADATA
tantivy_fork_arm-0.22.1.dist-info/WHEEL
tantivy_fork_arm-0.22.1.dist-info/licenses/LICENSE
tantivy/__init__.py
tantivy/tantivy.pyi
tantivy/py.typed
tantivy/tantivy.cpython-312-aarch64-linux-gnu.so
tantivy_fork_arm-0.22.1.dist-info/RECORD
