Metadata-Version: 2.4
Name: tantivy-fork-arm
Version: 0.22.1
Requires-Dist: nox ; extra == 'dev'
Provides-Extra: dev
License-File: LICENSE
Author: Damir Jelić <poljar@termina.org.uk>
Author-email: Damir Jelić <poljar@termina.org.uk>
License: MIT
Requires-Python: >=3.9
